<?xml version="1.0" encoding="utf-8" ?><dwsync><file name="client_8_gray.png" server="172.17.17.22//var/www/html/" local="3805793594" remote="3805793594" Dst="-1" /><file name="client_3_gray.png" server="172.17.17.22//var/www/html/" local="3805793594" remote="3805793594" Dst="-1" /><file name="client_2_gray.png" server="172.17.17.22//var/www/html/" local="3805793594" remote="3805793594" Dst="-1" /><file name="client_7.png" server="172.17.17.22//var/www/html/" local="3805793594" remote="3805793594" Dst="-1" /><file name="client_6.png" server="172.17.17.22//var/www/html/" local="3805793595" remote="3805793595" Dst="-1" /><file name="client_4.png" server="172.17.17.22//var/www/html/" local="3805793595" remote="3805793595" Dst="-1" /><file name="client_4_gray.png" server="172.17.17.22//var/www/html/" local="3805793595" remote="3805793595" Dst="-1" /><file name="client_5_gray.png" server="172.17.17.22//var/www/html/" local="3805793595" remote="3805793595" Dst="-1" /><file name="client_5.png" server="172.17.17.22//var/www/html/" local="3805793595" remote="3805793595" Dst="-1" /><file name="client_1.png" server="172.17.17.22//var/www/html/" local="3805793596" remote="3805793596" Dst="-1" /><file name="client_2.png" server="172.17.17.22//var/www/html/" local="3805793596" remote="3805793596" Dst="-1" /><file name="client_3.png" server="172.17.17.22//var/www/html/" local="3805793597" remote="3805793597" Dst="-1" /><file name="client_1_gray.png" server="172.17.17.22//var/www/html/" local="3805793597" remote="3805793597" Dst="-1" /><file name="client_8.png" server="172.17.17.22//var/www/html/" local="3805793598" remote="3805793598" Dst="-1" /><file name="client_7_gray.png" server="172.17.17.22//var/www/html/" local="3805793598" remote="3805793598" Dst="-1" /><file name="client_6_gray.png" server="172.17.17.22//var/www/html/" local="3805793598" remote="3805793598" Dst="-1" /></dwsync>